beaconclient/__init__.py
beaconclient/asyncio.py
beaconclient/config.py
beaconclient/protocol.py
beaconclient/py.typed
beaconclient/syncio.py
beaconclient/utils.py
beaconclient-1.0.3.dist-info/METADATA
beaconclient-1.0.3.dist-info/WHEEL
beaconclient-1.0.3.dist-info/top_level.txt
beaconclient-1.0.3.dist-info/RECORD
