Metadata-Version: 2.4
Name: beaconclient
Version: 1.0.3
Summary: Client to access to Beacon services
Author-email: BLISS team <bliss@esrf.fr>
License-Expression: LGPL-3.0-or-later
Project-URL: Homepage, https://gitlab.esrf.fr/bliss/beaconclient
Project-URL: Bug Tracker, https://gitlab.esrf.fr/bliss/beaconclient/issues
Classifier: Intended Audience :: Science/Research
Classifier: Programming Language :: Python :: 3
Requires-Python: >=3.9
Provides-Extra: dev
Requires-Dist: black; extra == "dev"
Requires-Dist: pytest; extra == "dev"
Requires-Dist: pytest-tcpclient; extra == "dev"
Requires-Dist: pytest-asyncio; extra == "dev"
Provides-Extra: ruamel
Requires-Dist: ruamel.yaml; extra == "ruamel"
